resume_exporter/__init__.py
resume_exporter/api_utils.py
resume_exporter/export_result.py
resume_exporter/export_supervisor.py
resume_exporter/export_worker.py
resume_exporter/printer.py
resume_exporter/profile_entity.py
resume_exporter/profile_retriever.py
resume_exporter/resume_exporter.py
riminder_resume_exporter-0.0.3.dist-info/METADATA
riminder_resume_exporter-0.0.3.dist-info/WHEEL
riminder_resume_exporter-0.0.3.dist-info/entry_points.txt
riminder_resume_exporter-0.0.3.dist-info/top_level.txt
riminder_resume_exporter-0.0.3.dist-info/RECORD
