Metadata-Version: 2.1
Name: riminder-resume-exporter
Version: 0.0.3
Summary: Riminder resume exporter.
Home-page: https://github.com/Riminder/riminder-resumes-exporter
Author: riminder
Author-email: contact@rimider.net
License: MIT
Platform: UNKNOWN
Requires-Python: >=3.5
Requires-Dist: riminder
